{
  "updatedAt": "2026-05-01T23:01:13.015201+00:00",
  "realtime": 67,
  "7day": {
    "users": 23193,
    "views": 46156,
    "sessions": 23250
  },
  "30day": {
    "users": 52371,
    "newUsers": 52240,
    "views": 106316,
    "sessions": 52417
  },
  "topPages": [
    {
      "label": "Home",
      "count": 51890
    },
    {
      "label": "NYC Building Checker",
      "count": 49672
    },
    {
      "label": "NYC Landlord Watch",
      "count": 154
    },
    {
      "label": "Tools",
      "count": 10
    },
    {
      "label": "NYC School Budget Tracker",
      "count": 8
    },
    {
      "label": "Impact",
      "count": 6
    },
    {
      "label": "About",
      "count": 4
    },
    {
      "label": "NYC Eviction Records",
      "count": 3
    }
  ],
  "sources": [
    {
      "name": "Organic Search",
      "count": 14152,
      "i": 0
    },
    {
      "name": "Organic Video",
      "count": 13493,
      "i": 1
    },
    {
      "name": "Direct",
      "count": 12742,
      "i": 2
    },
    {
      "name": "Referral",
      "count": 11829,
      "i": 3
    },
    {
      "name": "Unassigned",
      "count": 1387,
      "i": 4
    },
    {
      "name": "Organic Social",
      "count": 104,
      "i": 5
    },
    {
      "name": "Cross-network",
      "count": 3,
      "i": 6
    }
  ]
}