{
  "updatedAt": "2026-04-25T09:00:39.445294+00:00",
  "realtime": 77,
  "7day": {
    "users": 21669,
    "views": 43121,
    "sessions": 21545
  },
  "30day": {
    "users": 32543,
    "newUsers": 32495,
    "views": 67044,
    "sessions": 32578
  },
  "topPages": [
    {
      "label": "Home",
      "count": 32201
    },
    {
      "label": "NYC Building Checker",
      "count": 30139
    },
    {
      "label": "NYC Landlord Watch",
      "count": 158
    },
    {
      "label": "Tools",
      "count": 11
    },
    {
      "label": "NYC School Budget Tracker",
      "count": 8
    },
    {
      "label": "Impact",
      "count": 6
    },
    {
      "label": "About",
      "count": 4
    },
    {
      "label": "NYC Eviction Records",
      "count": 3
    }
  ],
  "sources": [
    {
      "name": "Organic Search",
      "count": 9379,
      "i": 0
    },
    {
      "name": "Organic Video",
      "count": 8249,
      "i": 1
    },
    {
      "name": "Direct",
      "count": 7695,
      "i": 2
    },
    {
      "name": "Referral",
      "count": 7189,
      "i": 3
    },
    {
      "name": "Unassigned",
      "count": 2222,
      "i": 4
    },
    {
      "name": "Organic Social",
      "count": 104,
      "i": 5
    },
    {
      "name": "Cross-network",
      "count": 7,
      "i": 6
    }
  ]
}