{
  "updatedAt": "2026-04-27T11:48:57.064026+00:00",
  "realtime": 56,
  "7day": {
    "users": 22231,
    "views": 43836,
    "sessions": 21836
  },
  "30day": {
    "users": 39216,
    "newUsers": 38838,
    "views": 79642,
    "sessions": 38364
  },
  "topPages": [
    {
      "label": "Home",
      "count": 38817
    },
    {
      "label": "NYC Building Checker",
      "count": 36657
    },
    {
      "label": "NYC Landlord Watch",
      "count": 158
    },
    {
      "label": "Tools",
      "count": 11
    },
    {
      "label": "NYC School Budget Tracker",
      "count": 8
    },
    {
      "label": "Impact",
      "count": 6
    },
    {
      "label": "About",
      "count": 4
    },
    {
      "label": "NYC Eviction Records",
      "count": 3
    }
  ],
  "sources": [
    {
      "name": "Organic Search",
      "count": 10647,
      "i": 0
    },
    {
      "name": "Organic Video",
      "count": 9763,
      "i": 1
    },
    {
      "name": "Direct",
      "count": 9473,
      "i": 2
    },
    {
      "name": "Referral",
      "count": 8624,
      "i": 3
    },
    {
      "name": "Unassigned",
      "count": 2392,
      "i": 4
    },
    {
      "name": "Organic Social",
      "count": 104,
      "i": 5
    },
    {
      "name": "Cross-network",
      "count": 3,
      "i": 6
    }
  ]
}