{
  "updatedAt": "2026-05-01T13:39:45.469212+00:00",
  "realtime": 69,
  "7day": {
    "users": 22072,
    "views": 44041,
    "sessions": 22059
  },
  "30day": {
    "users": 51196,
    "newUsers": 51164,
    "views": 104201,
    "sessions": 51180
  },
  "topPages": [
    {
      "label": "Home",
      "count": 50756
    },
    {
      "label": "NYC Building Checker",
      "count": 48634
    },
    {
      "label": "NYC Landlord Watch",
      "count": 154
    },
    {
      "label": "Tools",
      "count": 10
    },
    {
      "label": "NYC School Budget Tracker",
      "count": 8
    },
    {
      "label": "Impact",
      "count": 6
    },
    {
      "label": "About",
      "count": 4
    },
    {
      "label": "NYC Eviction Records",
      "count": 3
    }
  ],
  "sources": [
    {
      "name": "Organic Search",
      "count": 13889,
      "i": 0
    },
    {
      "name": "Organic Video",
      "count": 13206,
      "i": 1
    },
    {
      "name": "Direct",
      "count": 12486,
      "i": 2
    },
    {
      "name": "Referral",
      "count": 11583,
      "i": 3
    },
    {
      "name": "Unassigned",
      "count": 699,
      "i": 4
    },
    {
      "name": "Organic Social",
      "count": 104,
      "i": 5
    },
    {
      "name": "Cross-network",
      "count": 2,
      "i": 6
    }
  ]
}